seeder/__init__.py
seeder/seed.py
seeder/types.py
quick_seeders-0.2.4.dist-info/METADATA
quick_seeders-0.2.4.dist-info/WHEEL
quick_seeders-0.2.4.dist-info/top_level.txt
quick_seeders-0.2.4.dist-info/RECORD
