Metadata-Version: 2.2
Name: quick-seeders
Version: 0.2.4
Summary: Python package for generating seed data for testing and development
Author-email: Graham Burleigh <grahamburleigh6@gmail.com>
Requires-Dist: faker
